adhoconda/__init__.py
adhoconda/_common.py
adhoconda/_ext.py
adhoconda/_makenv.py
adhoconda/environment.yml
adhoconda-0.2.dist-info/LICENSE
adhoconda-0.2.dist-info/METADATA
adhoconda-0.2.dist-info/WHEEL
adhoconda-0.2.dist-info/entry_points.txt
adhoconda-0.2.dist-info/top_level.txt
adhoconda-0.2.dist-info/RECORD
