Metadata-Version: 2.1
Name: adhoconda
Version: 0.2
Summary: Ad hoc IPython kernels based on Conda environments, with on-the-fly dependency updates
Author-email: Benoit Hamelin <benoit@benoithamelin.com>
License: MIT License
Project-URL: Homepage, https://github.com/TutteInstitute/adhoconda
Classifier: Programming Language :: Python :: 3
Classifier: Intended Audience :: Developers
Classifier: License :: OSI Approved :: MIT License
Requires-Python: >=3.8
License-File: LICENSE
